{
  "date": "2026-04-05",
  "fetched_at": "2026-04-05T11:27:49.903029Z",
  "total_items": 150,
  "summary": "GOVINT collected 150 items from 4 sources on 2026-04-05.",
  "source_counts": {
    "CISA-KEV": 50,
    "NWS": 50,
    "CISA": 40,
    "DHS": 10
  },
  "category_counts": {
    "cybersecurity": 100,
    "public-safety": 60,
    "weather": 50,
    "ransomware": 2
  },
  "notable": [
    {
      "title": "National Historic Preservation Act, Section 106 - Public Comment Notice",
      "url": "https://www.dhs.gov/publication/national-historic-preservation-act-section-106-public-comment-notice",
      "source": "DHS"
    },
    {
      "title": "Congressional Budget Justification Fiscal Year (FY) 2027",
      "url": "https://www.dhs.gov/publication/congressional-budget-justification-fiscal-year-fy-2027",
      "source": "DHS"
    },
    {
      "title": "Fiscal Year (FY) 2027 Budget-in-Brief",
      "url": "https://www.dhs.gov/publication/fiscal-year-fy-2027-budget-brief",
      "source": "DHS"
    },
    {
      "title": "K2P Anniversary",
      "url": "https://www.dhs.gov/know2protect/anniversary",
      "source": "DHS"
    },
    {
      "title": "Markwayne Mullin",
      "url": "https://www.dhs.gov/markwayne-mullin",
      "source": "DHS"
    },
    {
      "title": "ICE Letter to Representative Escobar re: Interactions with ICE and ICE detainees",
      "url": "https://www.dhs.gov/publication/ice-letter-representative-escobar-re-interactions-ice-and-ice-detainees",
      "source": "DHS"
    },
    {
      "title": "Mike Fullerton",
      "url": "https://www.dhs.gov/person/mike-fullerton",
      "source": "DHS"
    },
    {
      "title": "U.S. Coast Guard Board for Correction of Military Records ruling",
      "url": "https://www.dhs.gov/publication/us-coast-guard-board-correction-military-records-ruling",
      "source": "DHS"
    },
    {
      "title": "Eric A. Ruark",
      "url": "https://www.dhs.gov/person/eric-ruark",
      "source": "DHS"
    },
    {
      "title": "Matthew Toplak",
      "url": "https://www.dhs.gov/person/matthew-toplak",
      "source": "DHS"
    }
  ]
}